[
  {
    "id": "property-001",
    "name": "The Grand Hotel Downtown",
    "bookingUrl": "https://www.booking.com/hotel/us/the-grand-downtown.html",
    "expediaUrl": "https://www.expedia.com/New-York-Hotels-The-Grand-Downtown.h12345678.Hotel-Information",
    "airbnbUrl": "https://www.airbnb.com/rooms/12345678",
    "googleUrl": "https://www.google.com/maps/place/The+Grand+Hotel/@40.7128,-74.0060,17z"
  },
  {
    "id": "property-002",
    "name": "Beachfront Villa",
    "bookingUrl": "https://www.booking.com/hotel/us/beachfront-villa.html",
    "expediaUrl": "https://www.expedia.com/...",
    "airbnbUrl": "https://www.airbnb.com/rooms/87654321",
    "googleUrl": "https://www.google.com/maps/place/Beachfront+Villa/..."
  }
]
