{
  "lastUpdated": "2026-06-07T19:59:31.619Z",
  "properties": {
    "sea-air-inn": {
      "name": "Sea Air Inn",
      "history": {
        "2026-06": {
          "label": "June 2026",
          "mode": "baseline",
          "scrapedAt": "2026-06-04T22:07:34.316Z",
          "platforms": {
            "booking": {
              "count": 62,
              "error": null
            },
            "expedia": {
              "count": 0,
              "error": null
            },
            "airbnb": {
              "count": null,
              "rawTotal": 286,
              "previousTotal": null,
              "previousMonth": null,
              "note": "No prior snapshot found — baseline stored. Delta available next month.",
              "error": null
            },
            "google": {
              "count": null,
              "error": null,
              "skipped": true,
              "note": "No URL configured"
            }
          }
        },
        "2026-05": {
          "label": "May 2026",
          "mode": "monthly",
          "scrapedAt": "2026-06-07T18:07:32.158Z",
          "platforms": {
            "booking": {
              "count": 75,
              "error": null
            },
            "expedia": {
              "count": 0,
              "error": null
            },
            "airbnb": {
              "count": null,
              "rawTotal": 289,
              "previousTotal": null,
              "previousMonth": null,
              "note": "No prior snapshot found — baseline stored. Delta available next month.",
              "error": null
            },
            "google": {
              "count": null,
              "error": null,
              "skipped": true,
              "note": "No URL configured"
            }
          }
        }
      }
    },
    "blufftop-inn": {
      "name": "Blufftop Inn",
      "history": {
        "2026-06": {
          "label": "June 2026",
          "mode": "baseline",
          "scrapedAt": "2026-06-04T22:15:38.753Z",
          "platforms": {
            "booking": {
              "count": 61,
              "error": null
            },
            "expedia": {
              "count": 0,
              "error": null
            },
            "airbnb": {
              "count": null,
              "rawTotal": 74,
              "previousTotal": null,
              "previousMonth": null,
              "note": "No prior snapshot found — baseline stored. Delta available next month.",
              "error": null
            },
            "google": {
              "count": null,
              "error": null,
              "skipped": true,
              "note": "No URL configured"
            }
          }
        },
        "2026-05": {
          "label": "May 2026",
          "mode": "monthly",
          "scrapedAt": "2026-06-07T18:15:34.662Z",
          "platforms": {
            "booking": {
              "count": 77,
              "error": null
            },
            "expedia": {
              "count": 0,
              "error": null
            },
            "airbnb": {
              "count": null,
              "rawTotal": 76,
              "previousTotal": null,
              "previousMonth": null,
              "note": "No prior snapshot found — baseline stored. Delta available next month.",
              "error": null
            },
            "google": {
              "count": null,
              "error": null,
              "skipped": true,
              "note": "No URL configured"
            }
          }
        }
      }
    },
    "harbor-house": {
      "name": "Harbor House",
      "history": {
        "2026-06": {
          "label": "June 2026",
          "mode": "baseline",
          "scrapedAt": "2026-06-04T22:23:35.041Z",
          "platforms": {
            "booking": {
              "count": 63,
              "error": null
            },
            "expedia": {
              "count": 0,
              "error": null
            },
            "airbnb": {
              "count": null,
              "rawTotal": 177,
              "previousTotal": null,
              "previousMonth": null,
              "note": "No prior snapshot found — baseline stored. Delta available next month.",
              "error": null
            },
            "google": {
              "count": null,
              "error": null,
              "skipped": true,
              "note": "No URL configured"
            }
          }
        },
        "2026-05": {
          "label": "May 2026",
          "mode": "monthly",
          "scrapedAt": "2026-06-07T18:23:44.136Z",
          "platforms": {
            "booking": {
              "count": 82,
              "error": null
            },
            "expedia": {
              "count": 0,
              "error": null
            },
            "airbnb": {
              "count": null,
              "rawTotal": 177,
              "previousTotal": null,
              "previousMonth": null,
              "note": "No prior snapshot found — baseline stored. Delta available next month.",
              "error": null
            },
            "google": {
              "count": null,
              "error": null,
              "skipped": true,
              "note": "No URL configured"
            }
          }
        }
      }
    },
    "bay-view-inn": {
      "name": "Bay View Inn",
      "history": {
        "2026-06": {
          "label": "June 2026",
          "mode": "baseline",
          "scrapedAt": "2026-06-04T22:31:23.577Z",
          "platforms": {
            "booking": {
              "count": 58,
              "error": null
            },
            "expedia": {
              "count": 0,
              "error": null
            },
            "airbnb": {
              "count": null,
              "rawTotal": 550,
              "previousTotal": null,
              "previousMonth": null,
              "note": "No prior snapshot found — baseline stored. Delta available next month.",
              "error": null
            },
            "google": {
              "count": null,
              "error": null,
              "skipped": true,
              "note": "No URL configured"
            }
          }
        },
        "2026-05": {
          "label": "May 2026",
          "mode": "monthly",
          "scrapedAt": "2026-06-07T18:31:39.081Z",
          "platforms": {
            "booking": {
              "count": 77,
              "error": null
            },
            "expedia": {
              "count": 0,
              "error": null
            },
            "airbnb": {
              "count": null,
              "rawTotal": 550,
              "previousTotal": null,
              "previousMonth": null,
              "note": "No prior snapshot found — baseline stored. Delta available next month.",
              "error": null
            },
            "google": {
              "count": null,
              "error": null,
              "skipped": true,
              "note": "No URL configured"
            }
          }
        }
      }
    },
    "avalon-inn": {
      "name": "Avalon Inn",
      "history": {
        "2026-06": {
          "label": "June 2026",
          "mode": "baseline",
          "scrapedAt": "2026-06-04T22:35:43.509Z",
          "platforms": {
            "booking": {
              "count": 25,
              "error": null
            },
            "expedia": {
              "count": 0,
              "error": null
            },
            "airbnb": {
              "count": null,
              "rawTotal": 529,
              "previousTotal": null,
              "previousMonth": null,
              "note": "No prior snapshot found — baseline stored. Delta available next month.",
              "error": null
            },
            "google": {
              "count": null,
              "error": null,
              "skipped": true,
              "note": "No URL configured"
            }
          }
        },
        "2026-05": {
          "label": "May 2026",
          "mode": "monthly",
          "scrapedAt": "2026-06-07T18:36:32.613Z",
          "platforms": {
            "booking": {
              "count": 39,
              "error": null
            },
            "expedia": {
              "count": 4,
              "error": null
            },
            "airbnb": {
              "count": null,
              "rawTotal": 529,
              "previousTotal": null,
              "previousMonth": null,
              "note": "No prior snapshot found — baseline stored. Delta available next month.",
              "error": null
            },
            "google": {
              "count": null,
              "error": null,
              "skipped": true,
              "note": "No URL configured"
            }
          }
        }
      }
    },
    "coastal-breeze": {
      "name": "Coastal Breeze",
      "history": {
        "2026-06": {
          "label": "June 2026",
          "mode": "baseline",
          "scrapedAt": "2026-06-04T22:41:06.134Z",
          "platforms": {
            "booking": {
              "count": 37,
              "error": null
            },
            "expedia": {
              "count": 0,
              "error": null
            },
            "airbnb": {
              "count": null,
              "rawTotal": 535,
              "previousTotal": null,
              "previousMonth": null,
              "note": "No prior snapshot found — baseline stored. Delta available next month.",
              "error": null
            },
            "google": {
              "count": null,
              "error": null,
              "skipped": true,
              "note": "No URL configured"
            }
          }
        },
        "2026-05": {
          "label": "May 2026",
          "mode": "monthly",
          "scrapedAt": "2026-06-07T18:41:52.640Z",
          "platforms": {
            "booking": {
              "count": 51,
              "error": null
            },
            "expedia": {
              "count": 0,
              "error": null
            },
            "airbnb": {
              "count": null,
              "rawTotal": 536,
              "previousTotal": null,
              "previousMonth": null,
              "note": "No prior snapshot found — baseline stored. Delta available next month.",
              "error": null
            },
            "google": {
              "count": null,
              "error": null,
              "skipped": true,
              "note": "No URL configured"
            }
          }
        }
      }
    },
    "rockview-inn": {
      "name": "Rockview Inn",
      "history": {
        "2026-06": {
          "label": "June 2026",
          "mode": "baseline",
          "scrapedAt": "2026-06-04T22:46:51.473Z",
          "platforms": {
            "booking": {
              "count": 37,
              "error": null
            },
            "expedia": {
              "count": 0,
              "error": null
            },
            "airbnb": {
              "count": null,
              "rawTotal": 141,
              "previousTotal": null,
              "previousMonth": null,
              "note": "No prior snapshot found — baseline stored. Delta available next month.",
              "error": null
            },
            "google": {
              "count": null,
              "error": null,
              "skipped": true,
              "note": "No URL configured"
            }
          }
        },
        "2026-05": {
          "label": "May 2026",
          "mode": "monthly",
          "scrapedAt": "2026-06-07T18:47:45.771Z",
          "platforms": {
            "booking": {
              "count": 47,
              "error": null
            },
            "expedia": {
              "count": 0,
              "error": null
            },
            "airbnb": {
              "count": null,
              "rawTotal": 141,
              "previousTotal": null,
              "previousMonth": null,
              "note": "No prior snapshot found — baseline stored. Delta available next month.",
              "error": null
            },
            "google": {
              "count": null,
              "error": null,
              "skipped": true,
              "note": "No URL configured"
            }
          }
        }
      }
    },
    "morro-shores-inn": {
      "name": "Morro Shores Inn",
      "history": {
        "2026-06": {
          "label": "June 2026",
          "mode": "baseline",
          "scrapedAt": "2026-06-04T22:55:18.377Z",
          "platforms": {
            "booking": {
              "count": 63,
              "error": null
            },
            "expedia": {
              "count": 0,
              "error": null
            },
            "airbnb": {
              "count": null,
              "rawTotal": 596,
              "previousTotal": null,
              "previousMonth": null,
              "note": "No prior snapshot found — baseline stored. Delta available next month.",
              "error": null
            },
            "google": {
              "count": null,
              "error": null,
              "skipped": true,
              "note": "No URL configured"
            }
          }
        },
        "2026-05": {
          "label": "May 2026",
          "mode": "monthly",
          "scrapedAt": "2026-06-07T18:56:13.133Z",
          "platforms": {
            "booking": {
              "count": 79,
              "error": null
            },
            "expedia": {
              "count": 0,
              "error": null
            },
            "airbnb": {
              "count": null,
              "rawTotal": 598,
              "previousTotal": null,
              "previousMonth": null,
              "note": "No prior snapshot found — baseline stored. Delta available next month.",
              "error": null
            },
            "google": {
              "count": null,
              "error": null,
              "skipped": true,
              "note": "No URL configured"
            }
          }
        }
      }
    },
    "hotel-avisa": {
      "name": "Hotel Avisa",
      "history": {
        "2026-06": {
          "label": "June 2026",
          "mode": "baseline",
          "scrapedAt": "2026-06-04T23:03:28.347Z",
          "platforms": {
            "booking": {
              "count": 61,
              "error": null
            },
            "expedia": {
              "count": 0,
              "error": null
            },
            "airbnb": {
              "count": null,
              "rawTotal": 88,
              "previousTotal": null,
              "previousMonth": null,
              "note": "No prior snapshot found — baseline stored. Delta available next month.",
              "error": null
            },
            "google": {
              "count": null,
              "error": null,
              "skipped": true,
              "note": "No URL configured"
            }
          }
        },
        "2026-05": {
          "label": "May 2026",
          "mode": "monthly",
          "scrapedAt": "2026-06-07T19:04:25.646Z",
          "platforms": {
            "booking": {
              "count": 82,
              "error": null
            },
            "expedia": {
              "count": 0,
              "error": null
            },
            "airbnb": {
              "count": null,
              "rawTotal": 89,
              "previousTotal": null,
              "previousMonth": null,
              "note": "No prior snapshot found — baseline stored. Delta available next month.",
              "error": null
            },
            "google": {
              "count": null,
              "error": null,
              "skipped": true,
              "note": "No URL configured"
            }
          }
        }
      }
    },
    "pacific-shores-inn": {
      "name": "Pacific Shores Inn",
      "history": {
        "2026-06": {
          "label": "June 2026",
          "mode": "baseline",
          "scrapedAt": "2026-06-04T23:15:51.124Z",
          "platforms": {
            "booking": {
              "count": 63,
              "error": null
            },
            "expedia": {
              "count": 0,
              "error": null
            },
            "airbnb": {
              "count": null,
              "rawTotal": 71,
              "previousTotal": null,
              "previousMonth": null,
              "note": "No prior snapshot found — baseline stored. Delta available next month.",
              "error": null
            },
            "google": {
              "count": 0,
              "error": null
            }
          }
        },
        "2026-05": {
          "label": "May 2026",
          "mode": "monthly",
          "scrapedAt": "2026-06-07T19:16:37.840Z",
          "platforms": {
            "booking": {
              "count": 85,
              "error": null
            },
            "expedia": {
              "count": 0,
              "error": null
            },
            "airbnb": {
              "count": null,
              "rawTotal": 71,
              "previousTotal": null,
              "previousMonth": null,
              "note": "No prior snapshot found — baseline stored. Delta available next month.",
              "error": null
            },
            "google": {
              "count": 0,
              "error": null
            }
          }
        }
      }
    },
    "ascot-suites": {
      "name": "Ascot Suites",
      "history": {
        "2026-06": {
          "label": "June 2026",
          "mode": "baseline",
          "scrapedAt": "2026-06-04T23:23:51.065Z",
          "platforms": {
            "booking": {
              "count": 66,
              "error": null
            },
            "expedia": {
              "count": 0,
              "error": null
            },
            "airbnb": {
              "count": null,
              "rawTotal": 5,
              "previousTotal": null,
              "previousMonth": null,
              "note": "No prior snapshot found — baseline stored. Delta available next month.",
              "error": null
            },
            "google": {
              "count": null,
              "error": null,
              "skipped": true,
              "note": "No URL configured"
            }
          }
        },
        "2026-05": {
          "label": "May 2026",
          "mode": "monthly",
          "scrapedAt": "2026-06-07T19:24:57.025Z",
          "platforms": {
            "booking": {
              "count": 95,
              "error": null
            },
            "expedia": {
              "count": 0,
              "error": null
            },
            "airbnb": {
              "count": null,
              "rawTotal": 5,
              "previousTotal": null,
              "previousMonth": null,
              "note": "No prior snapshot found — baseline stored. Delta available next month.",
              "error": null
            },
            "google": {
              "count": null,
              "error": null,
              "skipped": true,
              "note": "No URL configured"
            }
          }
        }
      }
    },
    "la-serena-inn": {
      "name": "La Serena Inn",
      "history": {
        "2026-06": {
          "label": "June 2026",
          "mode": "baseline",
          "scrapedAt": "2026-06-04T23:32:33.274Z",
          "platforms": {
            "booking": {
              "count": 60,
              "error": null
            },
            "expedia": {
              "count": 0,
              "error": null
            },
            "airbnb": {
              "count": null,
              "error": "Could not extract any review counts from Airbnb profile page"
            },
            "google": {
              "count": null,
              "error": null,
              "skipped": true,
              "note": "No URL configured"
            }
          }
        },
        "2026-05": {
          "label": "May 2026",
          "mode": "monthly",
          "scrapedAt": "2026-06-07T19:33:42.338Z",
          "platforms": {
            "booking": {
              "count": 71,
              "error": null
            },
            "expedia": {
              "count": 0,
              "error": null
            },
            "airbnb": {
              "count": null,
              "error": "Could not extract any review counts from Airbnb profile page"
            },
            "google": {
              "count": null,
              "error": null,
              "skipped": true,
              "note": "No URL configured"
            }
          }
        }
      }
    },
    "456-embarcadero": {
      "name": "456 Embarcadero",
      "history": {
        "2026-06": {
          "label": "June 2026",
          "mode": "baseline",
          "scrapedAt": "2026-06-04T23:37:53.994Z",
          "platforms": {
            "booking": {
              "count": 36,
              "error": null
            },
            "expedia": {
              "count": 0,
              "error": null
            },
            "airbnb": {
              "count": null,
              "rawTotal": 66,
              "previousTotal": null,
              "previousMonth": null,
              "note": "No prior snapshot found — baseline stored. Delta available next month.",
              "error": null
            },
            "google": {
              "count": null,
              "error": null,
              "skipped": true,
              "note": "No URL configured"
            }
          }
        },
        "2026-05": {
          "label": "May 2026",
          "mode": "monthly",
          "scrapedAt": "2026-06-07T19:39:17.012Z",
          "platforms": {
            "booking": {
              "count": 46,
              "error": null
            },
            "expedia": {
              "count": 0,
              "error": null
            },
            "airbnb": {
              "count": null,
              "rawTotal": 66,
              "previousTotal": null,
              "previousMonth": null,
              "note": "No prior snapshot found — baseline stored. Delta available next month.",
              "error": null
            },
            "google": {
              "count": null,
              "error": null,
              "skipped": true,
              "note": "No URL configured"
            }
          }
        }
      }
    },
    "marina-street-inn": {
      "name": "Marina Street Inn",
      "history": {
        "2026-06": {
          "label": "June 2026",
          "mode": "baseline",
          "scrapedAt": "2026-06-04T23:38:48.476Z",
          "platforms": {
            "booking": {
              "count": null,
              "error": null,
              "skipped": true,
              "note": "No URL configured"
            },
            "expedia": {
              "count": null,
              "error": null,
              "skipped": true,
              "note": "No URL configured"
            },
            "airbnb": {
              "count": null,
              "rawTotal": 120,
              "previousTotal": null,
              "previousMonth": null,
              "note": "No prior snapshot found — baseline stored. Delta available next month.",
              "error": null
            },
            "google": {
              "count": null,
              "error": null,
              "skipped": true,
              "note": "No URL configured"
            }
          }
        },
        "2026-05": {
          "label": "May 2026",
          "mode": "monthly",
          "scrapedAt": "2026-06-07T19:40:19.530Z",
          "platforms": {
            "booking": {
              "count": null,
              "error": null,
              "skipped": true,
              "note": "No URL configured"
            },
            "expedia": {
              "count": null,
              "error": null,
              "skipped": true,
              "note": "No URL configured"
            },
            "airbnb": {
              "count": null,
              "rawTotal": 120,
              "previousTotal": null,
              "previousMonth": null,
              "note": "No prior snapshot found — baseline stored. Delta available next month.",
              "error": null
            },
            "google": {
              "count": null,
              "error": null,
              "skipped": true,
              "note": "No URL configured"
            }
          }
        }
      }
    },
    "estero-inn": {
      "name": "Estero Inn",
      "history": {
        "2026-06": {
          "label": "June 2026",
          "mode": "baseline",
          "scrapedAt": "2026-06-04T23:39:58.665Z",
          "platforms": {
            "booking": {
              "count": null,
              "error": null,
              "skipped": true,
              "note": "No URL configured"
            },
            "expedia": {
              "count": null,
              "error": null,
              "skipped": true,
              "note": "No URL configured"
            },
            "airbnb": {
              "count": null,
              "rawTotal": 128,
              "previousTotal": null,
              "previousMonth": null,
              "note": "No prior snapshot found — baseline stored. Delta available next month.",
              "error": null
            },
            "google": {
              "count": null,
              "error": null,
              "skipped": true,
              "note": "No URL configured"
            }
          }
        },
        "2026-05": {
          "label": "May 2026",
          "mode": "monthly",
          "scrapedAt": "2026-06-07T19:41:30.113Z",
          "platforms": {
            "booking": {
              "count": null,
              "error": null,
              "skipped": true,
              "note": "No URL configured"
            },
            "expedia": {
              "count": null,
              "error": null,
              "skipped": true,
              "note": "No URL configured"
            },
            "airbnb": {
              "count": null,
              "rawTotal": 128,
              "previousTotal": null,
              "previousMonth": null,
              "note": "No prior snapshot found — baseline stored. Delta available next month.",
              "error": null
            },
            "google": {
              "count": null,
              "error": null,
              "skipped": true,
              "note": "No URL configured"
            }
          }
        }
      }
    },
    "landing-inn": {
      "name": "Landing Inn",
      "history": {
        "2026-06": {
          "label": "June 2026",
          "mode": "baseline",
          "scrapedAt": "2026-06-04T23:47:29.313Z",
          "platforms": {
            "booking": {
              "count": 64,
              "error": null
            },
            "expedia": {
              "count": 0,
              "error": null
            },
            "airbnb": {
              "count": null,
              "error": null,
              "skipped": true,
              "note": "No URL configured"
            },
            "google": {
              "count": null,
              "error": null,
              "skipped": true,
              "note": "No URL configured"
            }
          }
        },
        "2026-05": {
          "label": "May 2026",
          "mode": "monthly",
          "scrapedAt": "2026-06-07T19:49:01.842Z",
          "platforms": {
            "booking": {
              "count": 85,
              "error": null
            },
            "expedia": {
              "count": 0,
              "error": null
            },
            "airbnb": {
              "count": null,
              "error": null,
              "skipped": true,
              "note": "No URL configured"
            },
            "google": {
              "count": null,
              "error": null,
              "skipped": true,
              "note": "No URL configured"
            }
          }
        }
      }
    },
    "masterpiece-hotel": {
      "name": "Masterpiece Hotel",
      "history": {
        "2026-06": {
          "label": "June 2026",
          "mode": "baseline",
          "scrapedAt": "2026-06-04T23:55:11.042Z",
          "platforms": {
            "booking": {
              "count": 65,
              "error": null
            },
            "expedia": {
              "count": 0,
              "error": null
            },
            "airbnb": {
              "count": null,
              "error": null,
              "skipped": true,
              "note": "No URL configured"
            },
            "google": {
              "count": null,
              "error": null,
              "skipped": true,
              "note": "No URL configured"
            }
          }
        },
        "2026-05": {
          "label": "May 2026",
          "mode": "monthly",
          "scrapedAt": "2026-06-07T19:56:55.193Z",
          "platforms": {
            "booking": {
              "count": 82,
              "error": null
            },
            "expedia": {
              "count": 0,
              "error": null
            },
            "airbnb": {
              "count": null,
              "error": null,
              "skipped": true,
              "note": "No URL configured"
            },
            "google": {
              "count": null,
              "error": null,
              "skipped": true,
              "note": "No URL configured"
            }
          }
        }
      }
    },
    "holland-inn": {
      "name": "Holland Inn",
      "history": {
        "2026-06": {
          "label": "June 2026",
          "mode": "baseline",
          "scrapedAt": "2026-06-04T23:57:16.290Z",
          "platforms": {
            "booking": {
              "count": 7,
              "error": null
            },
            "expedia": {
              "count": 0,
              "error": null
            },
            "airbnb": {
              "count": null,
              "rawTotal": 27,
              "previousTotal": null,
              "previousMonth": null,
              "note": "No prior snapshot found — baseline stored. Delta available next month.",
              "error": null
            },
            "google": {
              "count": null,
              "error": null,
              "skipped": true,
              "note": "No URL configured"
            }
          }
        },
        "2026-05": {
          "label": "May 2026",
          "mode": "monthly",
          "scrapedAt": "2026-06-07T19:59:31.619Z",
          "platforms": {
            "booking": {
              "count": 17,
              "error": null
            },
            "expedia": {
              "count": 0,
              "error": null
            },
            "airbnb": {
              "count": null,
              "rawTotal": 31,
              "previousTotal": null,
              "previousMonth": null,
              "note": "No prior snapshot found — baseline stored. Delta available next month.",
              "error": null
            },
            "google": {
              "count": null,
              "error": null,
              "skipped": true,
              "note": "No URL configured"
            }
          }
        }
      }
    }
  }
}